polimap/__init__.py
polimap/__main__.py
polimap-0.0.1.dist-info/METADATA
polimap-0.0.1.dist-info/WHEEL
polimap-0.0.1.dist-info/entry_points.txt
polimap-0.0.1.dist-info/top_level.txt
polimap-0.0.1.dist-info/RECORD
